data_flow-0.3.dist-info/DESCRIPTION.rst
data_flow-0.3.dist-info/METADATA
data_flow-0.3.dist-info/RECORD
data_flow-0.3.dist-info/WHEEL
data_flow-0.3.dist-info/metadata.json
data_flow-0.3.dist-info/top_level.txt
dataflow/__init__.py
dataflow/datatypes.py
dataflow/exceptions.py
dataflow/flow.py
dataflow/promises.py
dataflow/utils.py
