Metadata-Version: 2.0
Name: data-flow
Version: 0.3
Summary: A system transform data consistently and easily
Home-page: https://github.com/LordFeratum/DataFlow
Author: Enrique Pina Monserrat
Author-email: lord.feratum@gmail.com
License: UNKNOWN
Download-URL: https://github.com/LordFeratum/DataFlow/archive/0.3.tar.gz
Platform: UNKNOWN
